polymetrix/TSNE_embeddings.py
polymetrix/__init__.py
polymetrix/constants.py
polymetrix/embedding.py
polymetrix/kennard_ecfp.py
polymetrix/kmeans.py
polymetrix/lococv.py
polymetrix/CONSAL/CONSAL.py
polymetrix/datasets/__init__.py
polymetrix/datasets/curated_tg_dataset.py
polymetrix/datasets/dataset.py
polymetrix/featurizers/__init__.py
polymetrix/featurizers/base_featurizer.py
polymetrix/featurizers/chemical_featurizer.py
polymetrix/featurizers/comparator.py
polymetrix/featurizers/molecule.py
polymetrix/featurizers/multiple_featurizer.py
polymetrix/featurizers/polymer.py
polymetrix/featurizers/sidechain_backbone_featurizer.py
polymetrix/pysr_train_size_plot/random_forest.py
polymetrix/pysr_train_size_plot/symbolic_regression.py
polymetrix/splitters/__init__.py
polymetrix/splitters/splitters.py
polymetrix/sybo_1000_r1_fixed_nr/sybo_valid.py
polymetrix/sybo_1500_r1_fixed_nr/sybo_valid.py
polymetrix/sybo_2000_r1_fixed_nr/sybo_valid.py
polymetrix/sybo_500_r1_fixed_nr/sybo_valid.py
polymetrix/symbolic_AD_boosting/sybo_AD.py
polymetrix/symbolic_boosting_30000/sybo_30000.py
polymetrix/symbolic_regression_boosting_sympy/symbolic_boosting_sympy.py
polymetrix-0.2.0.dist-info/METADATA
polymetrix-0.2.0.dist-info/WHEEL
polymetrix-0.2.0.dist-info/top_level.txt
polymetrix-0.2.0.dist-info/RECORD
