Metadata-Version: 2.4
Name: polymetrix
Version: 0.2.0
Summary: A framework for calculating descriptors for polymers
Author-email: Sreekanth Kunchapu <sreekanthkuncha@gmail.com>, Kevin Maik Jablonka <mail@kjablonka.com>
License: MIT
Keywords: Polymer,flexibility descriptors,Physics-based descriptors
Classifier: Development Status :: 3 - Alpha
Classifier: Intended Audience :: Science/Research
Classifier: Programming Language :: Python :: 3
Classifier: Programming Language :: Python :: 3.9
Classifier: Programming Language :: Python :: 3.10
Classifier: Programming Language :: Python :: 3.11
Classifier: Programming Language :: Python :: 3.12
Classifier: Intended Audience :: Science/Research
Classifier: Topic :: Scientific/Engineering
Classifier: Operating System :: Microsoft :: Windows
Classifier: Operating System :: Unix
Classifier: Operating System :: MacOS
Requires-Python: <3.13,>=3.9
Requires-Dist: networkx
Requires-Dist: numpy
Requires-Dist: pandarallel
Requires-Dist: pandas
Requires-Dist: radonpy-pypi
Requires-Dist: rdkit
Requires-Dist: matplotlib
Requires-Dist: mofdscribe
Requires-Dist: pystow
Provides-Extra: dev
Requires-Dist: jupyter; extra == "dev"
Requires-Dist: docformatter; extra == "dev"
Requires-Dist: pytest; extra == "dev"
Requires-Dist: pytest-cov; extra == "dev"
Requires-Dist: ruff; extra == "dev"
Requires-Dist: bump-my-version; extra == "dev"
Requires-Dist: mkdocs; extra == "dev"
Requires-Dist: mkdocs-material; extra == "dev"
Requires-Dist: mkdocstrings[python]; extra == "dev"
